pyploid/__init__.py
pyploid/algorithms/__init__.py
pyploid/algorithms/crossover/__init__.py
pyploid/algorithms/crossover/index.py
pyploid/algorithms/evolution/__init__.py
pyploid/algorithms/evolution/simple.py
pyploid/algorithms/meiosis/__init__.py
pyploid/algorithms/meiosis/even.py
pyploid/algorithms/meiosis/polyploid.py
pyploid/algorithms/population/__init__.py
pyploid/algorithms/population/constant.py
pyploid/algorithms/selection/__init__.py
pyploid/algorithms/selection/tournament.py
pyploid/algorithms/survival/__init__.py
pyploid/algorithms/survival/ratio.py
pyploid/genetics/__init__.py
pyploid/genetics/genes/__init__.py
pyploid/genetics/genes/math.py
pyploid/genetics/genes/value.py
pyploid/genetics/layouts/__init__.py
pyploid/genetics/layouts/attribute.py
pyploid/indices/__init__.py
pyploid/indices/full.py
pyploid/individual/__init__.py
pyploid/individual/trivial.py
pyploid/recording/__init__.py
pyploid/recording/types.py
pyploid/types/__init__.py
pyploid/types/algorithms/__init__.py
pyploid/types/algorithms/crossover.py
pyploid/types/algorithms/evolution.py
pyploid/types/algorithms/fitness.py
pyploid/types/algorithms/meiosis.py
pyploid/types/algorithms/mutation.py
pyploid/types/algorithms/reproduce.py
pyploid/types/algorithms/selection.py
pyploid/types/algorithms/survival.py
pyploid/types/cytogenetic_index.py
pyploid/types/gene.py
pyploid/types/individual.py
pyploid/types/layout.py
pyploid/types/primitive.py
pyploid-1.1.5.dist-info/LICENSE
pyploid-1.1.5.dist-info/METADATA
pyploid-1.1.5.dist-info/WHEEL
pyploid-1.1.5.dist-info/RECORD
